gerenuq/__init__.py
gerenuq/gerenuq.py
gerenuq/gerenuq_cl.py
gerenuq/gerenuq_cl_docker.py
gerenuq-0.2.7.dist-info/LICENSE
gerenuq-0.2.7.dist-info/METADATA
gerenuq-0.2.7.dist-info/WHEEL
gerenuq-0.2.7.dist-info/entry_points.txt
gerenuq-0.2.7.dist-info/top_level.txt
gerenuq-0.2.7.dist-info/RECORD
