Metadata-Version: 2.1
Name: gerenuq
Version: 0.2.7
Summary: Samfile long-read filtering script.
Home-page: https://github.com/abahcheli/gerenuq
Author: Alec Bahcheli
Author-email: abahchel@uwo.ca
License: UNKNOWN
Platform: UNKNOWN
Classifier: Programming Language :: Python :: 3
Classifier: License :: OSI Approved :: Academic Free License (AFL)
Classifier: Operating System :: OS Independent
Requires-Python: >=3.0
Requires-Dist: pysam
Requires-Dist: pandas
